{"20":{"totalRequests":189,"totalErrors":0,"totalTimeSeconds":10.010646231,"rps":19,"meanLatencyMs":6.6,"maxLatencyMs":62,"minLatencyMs":5,"percentiles":{"50":5,"90":8,"95":10,"99":54},"errorCodes":{}},"40":{"totalRequests":381,"totalErrors":0,"totalTimeSeconds":10.00121535,"rps":38,"meanLatencyMs":8.3,"maxLatencyMs":39,"minLatencyMs":6,"percentiles":{"50":7,"90":10,"95":13,"99":27},"errorCodes":{}},"60":{"totalRequests":544,"totalErrors":0,"totalTimeSeconds":10.000486983999998,"rps":54,"meanLatencyMs":8,"maxLatencyMs":39,"minLatencyMs":6,"percentiles":{"50":7,"90":9,"95":11,"99":23},"errorCodes":{"-1":1}},"80":{"totalRequests":787,"totalErrors":0,"totalTimeSeconds":10.000693273000001,"rps":79,"meanLatencyMs":8.3,"maxLatencyMs":58,"minLatencyMs":6,"percentiles":{"50":7,"90":9,"95":14,"99":32},"errorCodes":{}},"100":{"totalRequests":956,"totalErrors":0,"totalTimeSeconds":10.000663626,"rps":96,"meanLatencyMs":9,"maxLatencyMs":68,"minLatencyMs":6,"percentiles":{"50":7,"90":11,"95":18,"99":49},"errorCodes":{}},"120":{"totalRequests":1146,"totalErrors":0,"totalTimeSeconds":10.006332259,"rps":115,"meanLatencyMs":15.8,"maxLatencyMs":165,"minLatencyMs":6,"percentiles":{"50":7,"90":38,"95":76,"99":116},"errorCodes":{}},"140":{"totalRequests":1357,"totalErrors":0,"totalTimeSeconds":10.001437946,"rps":136,"meanLatencyMs":24.8,"maxLatencyMs":127,"minLatencyMs":6,"percentiles":{"50":10,"90":71,"95":99,"99":112},"errorCodes":{}},"160":{"totalRequests":1449,"totalErrors":0,"totalTimeSeconds":10.008907660999999,"rps":145,"meanLatencyMs":32.1,"maxLatencyMs":117,"minLatencyMs":7,"percentiles":{"50":13,"90":93,"95":100,"99":111},"errorCodes":{}},"180":{"totalRequests":1662,"totalErrors":0,"totalTimeSeconds":10.095972418999999,"rps":165,"meanLatencyMs":144.2,"maxLatencyMs":356,"minLatencyMs":8,"percentiles":{"50":177,"90":280,"95":301,"99":328},"errorCodes":{}},"200":{"totalRequests":1678,"totalErrors":0,"totalTimeSeconds":10.001673019,"rps":168,"meanLatencyMs":366.5,"maxLatencyMs":854,"minLatencyMs":8,"percentiles":{"50":336,"90":619,"95":757,"99":818},"errorCodes":{}},"220":{"totalRequests":1585,"totalErrors":0,"totalTimeSeconds":10.000810890999999,"rps":158,"meanLatencyMs":914.8,"maxLatencyMs":2025,"minLatencyMs":10,"percentiles":{"50":761,"90":1909,"95":1965,"99":2008},"errorCodes":{}},"240":{"totalRequests":1554,"totalErrors":0,"totalTimeSeconds":10.1043152,"rps":154,"meanLatencyMs":1132.4,"maxLatencyMs":2590,"minLatencyMs":9,"percentiles":{"50":1024,"90":2300,"95":2441,"99":2575},"errorCodes":{}},"260":{"totalRequests":1690,"totalErrors":0,"totalTimeSeconds":10.003346599,"rps":169,"meanLatencyMs":1505.5,"maxLatencyMs":3256,"minLatencyMs":10,"percentiles":{"50":1405,"90":2874,"95":2960,"99":3199},"errorCodes":{}},"280":{"totalRequests":1668,"totalErrors":0,"totalTimeSeconds":10.011955534,"rps":167,"meanLatencyMs":1584,"maxLatencyMs":3525,"minLatencyMs":11,"percentiles":{"50":1420,"90":3017,"95":3323,"99":3481},"errorCodes":{}},"300":{"totalRequests":1584,"totalErrors":0,"totalTimeSeconds":10.004371971000001,"rps":158,"meanLatencyMs":1775.8,"maxLatencyMs":3841,"minLatencyMs":10,"percentiles":{"50":1724,"90":3326,"95":3582,"99":3777},"errorCodes":{}},"320":{"totalRequests":1483,"totalErrors":0,"totalTimeSeconds":10.477214828,"rps":142,"meanLatencyMs":2206.8,"maxLatencyMs":4602,"minLatencyMs":11,"percentiles":{"50":2071,"90":4184,"95":4313,"99":4575},"errorCodes":{}},"340":{"totalRequests":1383,"totalErrors":0,"totalTimeSeconds":10.292824036,"rps":134,"meanLatencyMs":2755.2,"maxLatencyMs":5040,"minLatencyMs":638,"percentiles":{"50":2673,"90":4566,"95":4916,"99":5027},"errorCodes":{}},"360":{"totalRequests":1299,"totalErrors":0,"totalTimeSeconds":10.18839867,"rps":127,"meanLatencyMs":3345.3,"maxLatencyMs":5566,"minLatencyMs":1014,"percentiles":{"50":3334,"90":5076,"95":5138,"99":5562},"errorCodes":{}},"380":{"totalRequests":1057,"totalErrors":0,"totalTimeSeconds":11.22330465,"rps":94,"meanLatencyMs":3980.1,"maxLatencyMs":6326,"minLatencyMs":1669,"percentiles":{"50":3345,"90":6257,"95":6293,"99":6319},"errorCodes":{}},"400":{"totalRequests":661,"totalErrors":0,"totalTimeSeconds":10.59739184,"rps":62,"meanLatencyMs":6323.3,"maxLatencyMs":7423,"minLatencyMs":5078,"percentiles":{"50":6646,"90":7358,"95":7391,"99":7421},"errorCodes":{}},"420":{"totalRequests":786,"totalErrors":0,"totalTimeSeconds":10.009049341,"rps":79,"meanLatencyMs":3984.8,"maxLatencyMs":7254,"minLatencyMs":2055,"percentiles":{"50":3860,"90":4965,"95":5106,"99":7059},"errorCodes":{}},"440":{"totalRequests":1017,"totalErrors":0,"totalTimeSeconds":11.769568292,"rps":86,"meanLatencyMs":2210.5,"maxLatencyMs":4169,"minLatencyMs":72,"percentiles":{"50":1857,"90":3983,"95":4117,"99":4157},"errorCodes":{}},"460":{"totalRequests":1,"totalErrors":1,"totalTimeSeconds":12.490926072,"rps":0,"meanLatencyMs":4919,"maxLatencyMs":4918,"minLatencyMs":4918,"percentiles":{"50":4918,"90":4918,"95":4918,"99":4918},"errorCodes":{"-1":1}},"480":{"totalRequests":0,"totalErrors":0,"totalTimeSeconds":14.834437263,"rps":0,"meanLatencyMs":null,"maxLatencyMs":0,"minLatencyMs":999999,"percentiles":{"50":false,"90":false,"95":false,"99":false},"errorCodes":{}},"500":{"totalRequests":0,"totalErrors":0,"totalTimeSeconds":10.732276024,"rps":0,"meanLatencyMs":null,"maxLatencyMs":0,"minLatencyMs":999999,"percentiles":{"50":false,"90":false,"95":false,"99":false},"errorCodes":{"-1":1}},"520":{"totalRequests":0,"totalErrors":0,"totalTimeSeconds":11.293575895,"rps":0,"meanLatencyMs":null,"maxLatencyMs":0,"minLatencyMs":999999,"percentiles":{"50":false,"90":false,"95":false,"99":false},"errorCodes":{}}}
